webei/__init__.py
webei/core.py
webei-0.2.0.dist-info/METADATA
webei-0.2.0.dist-info/WHEEL
webei-0.2.0.dist-info/top_level.txt
webei-0.2.0.dist-info/RECORD
