Metadata-Version: 2.4
Name: webei
Version: 0.2.0
Summary: A Python-native UI kit for creating interactive web frontends with a fluent API.
Home-page: https://github.com/yourusername/webei
Author: Your Name
Author-email: you@example.com
Classifier: Development Status :: 3 - Alpha
Classifier: Intended Audience :: Developers
Classifier: License :: OSI Approved :: MIT License
Classifier: Programming Language :: Python :: 3
Classifier: Framework :: Flask
Classifier: Topic :: Software Development :: Libraries :: Python Modules
Requires-Dist: Flask>=1.0
Requires-Dist: Flask-SocketIO>=5.0
Dynamic: author
Dynamic: author-email
Dynamic: classifier
Dynamic: description
Dynamic: description-content-type
Dynamic: home-page
Dynamic: requires-dist
Dynamic: summary
